Workbook

Sheet Data
A2: Type | B2: Component | C2: Jan-18 | D2: Feb-18 | E2: Mar-18 | F2: Apr-18 | G2: May-18 | H2: Jun-18 | I2: Jul-18 | J2: Aug-18 | K2: Sep-18 | L2: Oct-18 | M2: Nov-18 | N2: Dec-18 | O2: Jan-19 | P2: Feb-19 | Q2: Mar-19 | R2: Apr-19 | S2: May-19 | T2: Jun-19 | U2: Jul-19 | V2: Aug-19 | W2: Sep-19 | X2: Oct-19 | Y2: Nov-19 | Z2: Dec-19 | AA2: Jan-20 | AB2: Feb-20 | AC2: Mar-20 | AD2: Apr-20 | AE2: May-20 | AF2: Jun-20 | AG2: Jul-20 | AH2: Aug-20 | AI2: Sep-20 | AJ2: Oct-20 | AK2: Nov-20 | AL2: Dec-20 | AM2: Jan-21
A3: Income | B3: Salary | C3: 30000 | D3: 30000 | E3: 30000 | F3: 30000 | G3: 30000 | H3: 30000 | I3: 30000 | J3: 30000 | K3: 35000 | L3: 35000 | M3: 35000 | N3: 35000 | O3: 35000 | P3: 35000 | Q3: 35000 | R3: 35000 | S3: 35000 | T3: 35000 | U3: 35000 | V3: 35000 | W3: 35000 | X3: 35000 | Y3: 35000 | Z3: 35000 | AA3: 43000 | AB3: 43000 | AC3: 43000 | AD3: 43000 | AE3: 43000 | AF3: 43000 | AG3: 43000 | AH3: 43000 | AI3: 43000 | AJ3: 43000 | AK3: 51500 | AL3: 51500 | AM3: 51500
A4: Income | B4: Source 2 | C4: 1000 | D4: 1000 | E4: 1000 | F4: 1000 | G4: 1000 | H4: 1000 | I4: 1000 | J4: 1000 | K4: 1000 | L4: 1000 | M4: 1000 | N4: 1000 | O4: 1000 | P4: 4000 | Q4: 4000 | R4: 4000 | S4: 4000 | T4: 4000 | U4: 4000 | V4: 4000 | W4: 4000 | X4: 4000 | Y4: 4000 | Z4: 4000 | AA4: 4000 | AB4: 4000 | AC4: 4000 | AD4: 4000 | AE4: 4000 | AF4: 4000 | AG4: 6000 | AH4: 6000 | AI4: 6000 | AJ4: 6000 | AK4: 6000 | AL4: 6000 | AM4: 6000
A5: Savings | B5: Mutual funds | C5: 5000 | D5: 5000 | E5: 5000 | F5: 5000 | G5: 5000 | H5: 5000 | I5: 5000 | J5: 5000 | K5: 5000 | L5: 5000 | M5: 5000 | N5: 7000 | O5: 7000 | P5: 7000 | Q5: 7000 | R5: 7000 | S5: 7000 | T5: 7000 | U5: 7000 | V5: 7000 | W5: 7000 | X5: 7000 | Y5: 7000 | Z5: 0 | AA5: 7000 | AB5: 7000 | AC5: 7000 | AD5: 7000 | AE5: 7000 | AF5: 7000 | AG5: 7000 | AH5: 7000 | AI5: 7000 | AJ5: 7000 | AK5: 8000 | AL5: 8000 | AM5: 8000
A6: Savings | B6: Emergency Fund | C6: 2000 | D6: 2000 | E6: 2000 | F6: 2000 | G6: 2000 | H6: 2000 | I6: 2000 | J6: 0 | K6: 0 | L6: 2000 | M6: 2000 | N6: 2000 | O6: 2000 | P6: 2000 | Q6: 2000 | R6: 2000 | S6: 2000 | T6: 2000 | U6: 2000 | V6: 1000 | W6: 0 | X6: 0 | Y6: 0 | Z6: 0 | AA6: 0 | AB6: 0 | AC6: 0 | AD6: 0 | AE6: 2000 | AF6: 0 | AG6: 1000 | AH6: 1000 | AI6: 1000 | AJ6: 1000 | AK6: 2000 | AL6: 1000 | AM6: 3000
A7: Savings | B7: Fixed Deposit | C7: 2000 | D7: 2000 | E7: 2000 | F7: 2000 | G7: 2000 | H7: 2000 | I7: 2000 | J7: 2000 | K7: 0 | L7: 2000 | M7: 0 | N7: 0 | O7: 0 | P7: 2000 | Q7: 2000 | R7: 2000 | S7: 2000 | T7: 1000 | U7: 1000 | V7: 1000 | W7: 2000 | X7: 0 | Y7: 0 | Z7: 0 | AA7: 0 | AB7: 0 | AC7: 0 | AD7: 0 | AE7: 0 | AF7: 2000 | AG7: 0 | AH7: 0 | AI7: 2000 | AJ7: 2000 | AK7: 2500 | AL7: 2500 | AM7: 2500
A8: Savings | B8: Liquid Cash | C8: =SUM(C3:C4)-SUM(C5:C7)-SUM(C9:C14) | D8: =SUM(D3:D4)-SUM(D5:D7)-SUM(D9:D14) | E8: =SUM(E3:E4)-SUM(E5:E7)-SUM(E9:E14) | F8: =SUM(F3:F4)-SUM(F5:F7)-SUM(F9:F14) | G8: =SUM(G3:G4)-SUM(G5:G7)-SUM(G9:G14) | H8: =SUM(H3:H4)-SUM(H5:H7)-SUM(H9:H14) | I8: =SUM(I3:I4)-SUM(I5:I7)-SUM(I9:I14) | J8: =SUM(J3:J4)-SUM(J5:J7)-SUM(J9:J14) | ... AM8: =SUM(AM3:AM4)-SUM(AM5:AM7)-SUM(AM9:AM14)
A9: Expense | B9: House Rent | C9: 10000 | D9: 10000 | E9: 10000 | F9: 10000 | G9: 10000 | H9: 10000 | I9: 12000 | J9: 12000 | K9: 12000 | L9: 12000 | M9: 12000 | N9: 12000 | O9: 12000 | P9: 12000 | Q9: 12000 | R9: 12000 | S9: 12000 | T9: 12000 | U9: 12000 | V9: 12000 | W9: 12000 | X9: 12000 | Y9: 15000 | Z9: 15000 | AA9: 15000 | AB9: 15000 | AC9: 15000 | AD9: 15000 | AE9: 15000 | AF9: 15000 | AG9: 15000 | AH9: 15000 | AI9: 15000 | AJ9: 15000 | AK9: 15000 | AL9: 15000 | AM9: 16000
A10: Expense | B10: Groceries & Food | C10: 6000 | D10: 6000 | E10: 6000 | F10: 6000 | G10: 6000 | H10: 6000 | I10: 6000 | J10: 6000 | K10: 6000 | L10: 6000 | M10: 6000 | N10: 8000 | O10: 8000 | P10: 7000 | Q10: 7000 | R10: 7000 | S10: 7000 | T10: 7000 | U10: 7000 | V10: 7000 | W10: 8000 | X10: 8000 | Y10: 8000 | Z10: 10000 | AA10: 10000 | AB10: 10000 | AC10: 10000 | AD10: 8000 | AE10: 8000 | AF10: 8000 | AG10: 10000 | AH10: 10000 | AI10: 10000 | AJ10: 8000 | AK10: 10000 | AL10: 10000 | AM10: 9000
A11: Expense | B11: Health | C11: 1000 | D11: 1000 | E11: 1000 | F11: 1000 | G11: 1000 | H11: 1000 | I11: 1000 | J11: 1000 | K11: 1000 | L11: 1000 | M11: 1000 | N11: 1000 | O11: 3000 | P11: 1500 | Q11: 1500 | R11: 1500 | S11: 1500 | T11: 1500 | U11: 1500 | V11: 1500 | W11: 1500 | X11: 1500 | Y11: 1500 | Z11: 3000 | AA11: 3000 | AB11: 3000 | AC11: 3000 | AD11: 3000 | AE11: 3000 | AF11: 3000 | AG11: 3000 | AH11: 3000 | AI11: 3000 | AJ11: 3000 | AK11: 3000 | AL11: 4000 | AM11: 3000
A12: Expense | B12: EMIs | C12: 2500 | D12: 2500 | E12: 2500 | F12: 2500 | G12: 2500 | H12: 2500 | I12: 2500 | J12: 2500 | K12: 5000 | L12: 5000 | M12: 5000 | N12: 5000 | O12: 5000 | P12: 6000 | Q12: 6000 | R12: 6000 | S12: 6000 | T12: 6000 | U12: 7000 | V12: 7000 | W12: 7000 | X12: 7000 | Y12: 7000 | Z12: 7000 | AA12: 10000 | AB12: 10000 | AC12: 10000 | AD12: 10000 | AE12: 10000 | AF12: 10000 | AG12: 10000 | AH12: 10000 | AI12: 10000 | AJ12: 10000 | AK12: 12000 | AL12: 12000 | AM12: 12000
A13: Expense | B13: Leisure | C13: 500 | D13: 1500 | E13: 500 | F13: 1500 | G13: 500 | H13: 1500 | I13: 500 | J13: 1500 | K13: 4000 | L13: 1500 | M13: 1500 | N13: 1500 | O13: 0 | P13: 0 | Q13: 0 | R13: 1000 | S13: 1000 | T13: 1000 | U13: 1500 | V13: 1500 | W13: 1500 | X13: 1500 | Y13: 1500 | Z13: 1500 | AA13: 1500 | AB13: 1500 | AC13: 1500 | AD13: 1500 | AE13: 1500 | AF13: 500 | AG13: 1500 | AH13: 3000 | AI13: 1500 | AJ13: 1500 | AK13: 1500 | AL13: 1500 | AM13: 1500
A14: Expense | B14: Shopping | C14: 1000 | D14: 1000 | E14: 1000 | F14: 1000 | G14: 1000 | H14: 1000 | I14: 1000 | J14: 1000 | K14: 2000 | L14: 1000 | M14: 1000 | N14: 1000 | O14: 0 | P14: 0 | Q14: 0 | R14: 0 | S14: 0 | T14: 1000 | U14: 0 | V14: 0 | W14: 0 | X14: 1000 | Y14: 1000 | Z14: 2000 | AA14: 2000 | AB14: 2000 | AC14: 500 | AD14: 2000 | AE14: 2000 | AF14: 0 | AG14: 3000 | AH14: 2000 | AI14: 2000 | AJ14: 2000 | AK14: 2000 | AL14: 3000 | AM14: 3000

Sheet USD
A1: Exchange rate (INR per USD) | B1: 88 | C1: Edit B1 to update all USD conversions.
A2: Type | B2: Component | C2: =Data!C2/$B$1 | D2: =Data!D2/$B$1 | E2: =Data!E2/$B$1 | F2: =Data!F2/$B$1 | G2: =Data!G2/$B$1 | H2: =Data!H2/$B$1 | I2: =Data!I2/$B$1 | J2: =Data!J2/$B$1 | ... AM2: =Data!AM2/$B$1
A3: Income | B3: Salary | C3: =Data!C3/$B$1 | D3: =Data!D3/$B$1 | E3: =Data!E3/$B$1 | F3: =Data!F3/$B$1 | G3: =Data!G3/$B$1 | H3: =Data!H3/$B$1 | I3: =Data!I3/$B$1 | J3: =Data!J3/$B$1 | ... AM3: =Data!AM3/$B$1
A4: Income | B4: Source 2 | C4: =Data!C4/$B$1 | D4: =Data!D4/$B$1 | E4: =Data!E4/$B$1 | F4: =Data!F4/$B$1 | G4: =Data!G4/$B$1 | H4: =Data!H4/$B$1 | I4: =Data!I4/$B$1 | J4: =Data!J4/$B$1 | ... AM4: =Data!AM4/$B$1
A5: Savings | B5: Mutual funds | C5: =Data!C5/$B$1 | D5: =Data!D5/$B$1 | E5: =Data!E5/$B$1 | F5: =Data!F5/$B$1 | G5: =Data!G5/$B$1 | H5: =Data!H5/$B$1 | I5: =Data!I5/$B$1 | J5: =Data!J5/$B$1 | ... AM5: =Data!AM5/$B$1
A6: Savings | B6: Emergency Fund | C6: =Data!C6/$B$1 | D6: =Data!D6/$B$1 | E6: =Data!E6/$B$1 | F6: =Data!F6/$B$1 | G6: =Data!G6/$B$1 | H6: =Data!H6/$B$1 | I6: =Data!I6/$B$1 | J6: =Data!J6/$B$1 | ... AM6: =Data!AM6/$B$1
A7: Savings | B7: Fixed Deposit | C7: =Data!C7/$B$1 | D7: =Data!D7/$B$1 | E7: =Data!E7/$B$1 | F7: =Data!F7/$B$1 | G7: =Data!G7/$B$1 | H7: =Data!H7/$B$1 | I7: =Data!I7/$B$1 | J7: =Data!J7/$B$1 | ... AM7: =Data!AM7/$B$1
A8: Savings | B8: Liquid Cash | C8: =Data!C8/$B$1 | D8: =Data!D8/$B$1 | E8: =Data!E8/$B$1 | F8: =Data!F8/$B$1 | G8: =Data!G8/$B$1 | H8: =Data!H8/$B$1 | I8: =Data!I8/$B$1 | J8: =Data!J8/$B$1 | ... AM8: =Data!AM8/$B$1
A9: Expense | B9: House Rent | C9: =Data!C9/$B$1 | D9: =Data!D9/$B$1 | E9: =Data!E9/$B$1 | F9: =Data!F9/$B$1 | G9: =Data!G9/$B$1 | H9: =Data!H9/$B$1 | I9: =Data!I9/$B$1 | J9: =Data!J9/$B$1 | ... AM9: =Data!AM9/$B$1
A10: Expense | B10: Groceries & Food | C10: =Data!C10/$B$1 | D10: =Data!D10/$B$1 | E10: =Data!E10/$B$1 | F10: =Data!F10/$B$1 | G10: =Data!G10/$B$1 | H10: =Data!H10/$B$1 | I10: =Data!I10/$B$1 | J10: =Data!J10/$B$1 | ... AM10: =Data!AM10/$B$1
A11: Expense | B11: Health | C11: =Data!C11/$B$1 | D11: =Data!D11/$B$1 | E11: =Data!E11/$B$1 | F11: =Data!F11/$B$1 | G11: =Data!G11/$B$1 | H11: =Data!H11/$B$1 | I11: =Data!I11/$B$1 | J11: =Data!J11/$B$1 | ... AM11: =Data!AM11/$B$1
A12: Expense | B12: EMIs | C12: =Data!C12/$B$1 | D12: =Data!D12/$B$1 | E12: =Data!E12/$B$1 | F12: =Data!F12/$B$1 | G12: =Data!G12/$B$1 | H12: =Data!H12/$B$1 | I12: =Data!I12/$B$1 | J12: =Data!J12/$B$1 | ... AM12: =Data!AM12/$B$1
A13: Expense | B13: Leisure | C13: =Data!C13/$B$1 | D13: =Data!D13/$B$1 | E13: =Data!E13/$B$1 | F13: =Data!F13/$B$1 | G13: =Data!G13/$B$1 | H13: =Data!H13/$B$1 | I13: =Data!I13/$B$1 | J13: =Data!J13/$B$1 | ... AM13: =Data!AM13/$B$1
A14: Expense | B14: Shopping | C14: =Data!C14/$B$1 | D14: =Data!D14/$B$1 | E14: =Data!E14/$B$1 | F14: =Data!F14/$B$1 | G14: =Data!G14/$B$1 | H14: =Data!H14/$B$1 | I14: =Data!I14/$B$1 | J14: =Data!J14/$B$1 | ... AM14: =Data!AM14/$B$1
